vertica_highcharts/__init__.py
vertica_highcharts/ipynb.py
vertica_highcharts/version.py
vertica_highcharts/highcharts/__init__.py
vertica_highcharts/highcharts/common.py
vertica_highcharts/highcharts/highchart_types.py
vertica_highcharts/highcharts/highcharts.py
vertica_highcharts/highcharts/options.py
vertica_highcharts/highcharts/templates/base.html
vertica_highcharts/highcharts/templates/content.html
vertica_highcharts/highcharts/templates/page.html
vertica_highcharts/highcharts/templates/test.html
vertica_highcharts/highmaps/__init__.py
vertica_highcharts/highmaps/common.py
vertica_highcharts/highmaps/highmap_helper.py
vertica_highcharts/highmaps/highmap_types.py
vertica_highcharts/highmaps/highmaps.py
vertica_highcharts/highmaps/options.py
vertica_highcharts/highmaps/templates/base.html
vertica_highcharts/highmaps/templates/content.html
vertica_highcharts/highmaps/templates/page.html
vertica_highcharts/highmaps/templates/test.html
vertica_highcharts/highstock/__init__.py
vertica_highcharts/highstock/common.py
vertica_highcharts/highstock/highstock.py
vertica_highcharts/highstock/highstock_helper.py
vertica_highcharts/highstock/highstock_types.py
vertica_highcharts/highstock/options.py
vertica_highcharts/highstock/templates/base.html
vertica_highcharts/highstock/templates/content.html
vertica_highcharts/highstock/templates/page.html
vertica_highcharts/highstock/templates/test.html
vertica_highcharts-0.1.4.dist-info/LICENSE
vertica_highcharts-0.1.4.dist-info/METADATA
vertica_highcharts-0.1.4.dist-info/WHEEL
vertica_highcharts-0.1.4.dist-info/top_level.txt
vertica_highcharts-0.1.4.dist-info/RECORD
