Metadata-Version: 2.1
Name: vertica-highcharts
Version: 0.1.4
Summary: Python Highcharts wrapper
Home-page: https://github.com/vertica/vertica-highcharts
Download-URL: https://github.com/vertica/vertica-highcharts/releases/tag/0.1.4
Author: Kyper Developers
Author-email: developers@kyperdata.com
Keywords: python,ipython,highcharts,chart,visualization,graph,javascript,html
Classifier: Framework :: IPython
Classifier: Intended Audience :: Developers
Classifier: Intended Audience :: Financial and Insurance Industry
Classifier: Intended Audience :: Science/Research
Classifier: License :: OSI Approved :: MIT License
Classifier: Programming Language :: Python
Classifier: Programming Language :: Python :: 3
License-File: LICENSE
Requires-Dist: Jinja2
Requires-Dist: future
